README.rst
setup.py
crispor_cli/__init__.py
crispor_cli/crispor.py
crispor_cli/microHomScore.py
crispor_cli.egg-info/PKG-INFO
crispor_cli.egg-info/SOURCES.txt
crispor_cli.egg-info/dependency_links.txt
crispor_cli.egg-info/top_level.txt
crispor_cli/functions/__init__.py
crispor_cli/functions/basic_imports.py
crispor_cli/functions/batch_functions.py
crispor_cli/functions/bio_functions.py
crispor_cli/functions/cleanup_functions.py
crispor_cli/functions/common_functions.py
crispor_cli/functions/constants.py
crispor_cli/functions/crisporEffScores.py
crispor_cli/functions/doenchScore.py
crispor_cli/functions/fasta_functions.py
crispor_cli/functions/finishing_functions.py
crispor_cli/functions/get_offtargets.py
crispor_cli/functions/parser_functions.py
crispor_cli/functions/scoring_functions.py
crispor_cli/functions/sequence_helper_functions.py
crispor_cli/functions/submit_process.py