Metadata-Version: 1.0
Name: crispor-cli
Version: 0.1.1
Summary: Command line tool for crispr offtarget finding extracted from crispor website
Home-page: https://github.com/ElucidataInc/crispor-cli
Author: Kailash Yadav
Author-email: kailash.yadav@elucidata.io
License: The source code in crispor.py and crisporEffScores.py ("the code") is under
